yta_ai_prodia/__init__.py
yta_ai_prodia-0.0.2.dist-info/LICENSE
yta_ai_prodia-0.0.2.dist-info/METADATA
yta_ai_prodia-0.0.2.dist-info/WHEEL
yta_ai_prodia-0.0.2.dist-info/RECORD
